gewechat_client/__init__.py
gewechat_client/client.py
gewechat_client/api/__init__.py
gewechat_client/api/contact_api.py
gewechat_client/api/download_api.py
gewechat_client/api/favor_api.py
gewechat_client/api/group_api.py
gewechat_client/api/label_api.py
gewechat_client/api/login_api.py
gewechat_client/api/message_api.py
gewechat_client/api/personal_api.py
gewechat_client/util/__init__.py
gewechat_client/util/http_util.py
gewechat_client/util/terminal_printer.py
gewechat_client-0.2.2.dist-info/licenses/LICENSE
gewechat_client-0.2.2.dist-info/METADATA
gewechat_client-0.2.2.dist-info/WHEEL
gewechat_client-0.2.2.dist-info/top_level.txt
gewechat_client-0.2.2.dist-info/RECORD
