Metadata-Version: 2.4
Name: gewechat-client
Version: 0.2.2
Summary: A package for interacting with the Gewechat API
Home-page: https://github.com/hanfangyuan4396/gewechat-python
Author: hanfangyuan
Author-email: i@hanfangyuan.cn
License: Apache-2.0
Keywords: gewechat api client
Classifier: Programming Language :: Python :: 3
Classifier: License :: OSI Approved :: Apache Software License
Classifier: Operating System :: OS Independent
Requires-Python: >=3.6
License-File: LICENSE
Requires-Dist: requests
Requires-Dist: qrcode==7.4.2
Dynamic: author
Dynamic: author-email
Dynamic: classifier
Dynamic: description
Dynamic: description-content-type
Dynamic: home-page
Dynamic: keywords
Dynamic: license
Dynamic: license-file
Dynamic: requires-dist
Dynamic: requires-python
Dynamic: summary
